<BlockNode>
    <StatList>
        <Assignment>
            <VarList>
                <Variable var="table1"/>
            </VarList>
            <ExpList>
                <TableConstructor>
                    <FieldList>
                        <FieldLeftRightExpression>
                            <leftExpression operation="ADD">
                                <PrefixExpression>
                                    <PrefixExpressionVariable>
                                        <Variable var="a"/>
                                    </PrefixExpressionVariable>
                                </PrefixExpression>
                                <PrefixExpression>
                                    <PrefixExpressionVariable>
                                        <Variable var="b"/>
                                    </PrefixExpressionVariable>
                                </PrefixExpression>
                            </leftExpression>
                            <rightExpression operation="ADD">
                                <PrefixExpression>
                                    <PrefixExpressionVariable>
                                        <Variable var="a"/>
                                    </PrefixExpressionVariable>
                                </PrefixExpression>
                                <PrefixExpression>
                                    <PrefixExpressionVariable>
                                        <Variable var="b"/>
                                    </PrefixExpressionVariable>
                                </PrefixExpression>
                            </rightExpression>
                        </FieldLeftRightExpression>
                    </FieldList>
                </TableConstructor>
            </ExpList>
        </Assignment>
    </StatList>
</BlockNode>